bibtexgen/__init__.py
bibtexgen/entry.py
bibtexgen/utils.py
bibtexgen-0.0.2.dist-info/entry_points.txt
bibtexgen-0.0.2.dist-info/LICENSE
bibtexgen-0.0.2.dist-info/WHEEL
bibtexgen-0.0.2.dist-info/METADATA
bibtexgen-0.0.2.dist-info/RECORD
